youmadeit
